allure_subtests/__init__.py
allure_subtests/allure_subtest_plugin.py
allure_subtests/py.typed
allure_subtests-0.1.9.dist-info/entry_points.txt
allure_subtests-0.1.9.dist-info/LICENSE.txt
allure_subtests-0.1.9.dist-info/METADATA
allure_subtests-0.1.9.dist-info/WHEEL
allure_subtests-0.1.9.dist-info/RECORD
