Metadata-Version: 2.1
Name: allure-subtests
Version: 0.1.9
Summary: update readme demo according to code change
Author: zhoukai83
Requires-Python: >=3.8
Classifier: Programming Language :: Python :: 3
Classifier: Programming Language :: Python :: 3.8
Classifier: Programming Language :: Python :: 3.9
Classifier: Programming Language :: Python :: 3.10
Classifier: Programming Language :: Python :: 3.11
Classifier: Programming Language :: Python :: 3.12
Requires-Dist: allure-pytest (>=2.1)
Requires-Dist: loguru (>=0.4)
Requires-Dist: pytest (>=7.0)
Requires-Dist: pytest-check (>=2.3.1,<3.0.0)
Requires-Dist: requests (>=2.32.3,<3.0.0)
